gerrit/__init__.py
gerrit/filters.py
gerrit/reviews.py
gerrit/ssh.py
python_gerrit-0.0.2.dist-info/top_level.txt
python_gerrit-0.0.2.dist-info/METADATA
python_gerrit-0.0.2.dist-info/DESCRIPTION.rst
python_gerrit-0.0.2.dist-info/pydist.json
python_gerrit-0.0.2.dist-info/WHEEL
python_gerrit-0.0.2.dist-info/RECORD
