Metadata-Version: 2.0
Name: python-gerrit
Version: 0.0.2
Summary: Gerrit SSH Lib
Home-page: https://github.com/FlaPer87/python-gerrit
Author: Flavio Percoco
Author-email: flaper87@flaper87.org
License: Apache License v2
Platform: Any
Classifier: Intended Audience :: Developers
Classifier: Natural Language :: English
Classifier: License :: OSI Approved :: Apache Software License
Classifier: Programming Language :: Python
Classifier: Programming Language :: Python :: 2.6
Classifier: Programming Language :: Python :: 2.7
Requires-Dist: distribute
Requires-Dist: paramiko
